dify_file_parser-1.0.0.dist-info/licenses/LICENSE
file_parser/__init__.py
file_parser/base.py
file_parser/cli.py
file_parser/file_parser.py
file_parser/config/ocr_config.py
file_parser/ocr/__init__.py
file_parser/ocr/base_ocr.py
file_parser/ocr/ocr_manager.py
file_parser/ocr/tesseract_ocr.py
file_parser/parsers/__init__.py
file_parser/parsers/csv_parser.py
file_parser/parsers/excel_parser.py
file_parser/parsers/image_parser.py
file_parser/parsers/pdf_parser.py
file_parser/parsers/ppt_parser.py
file_parser/parsers/text_parser.py
file_parser/parsers/word_parser.py
file_parser/utils/__init__.py
file_parser/utils/file_utils.py
tests/__init__.py
tests/test_file_parser.py
tests/test_parsers.py
dify_file_parser-1.0.0.dist-info/METADATA
dify_file_parser-1.0.0.dist-info/WHEEL
dify_file_parser-1.0.0.dist-info/entry_points.txt
dify_file_parser-1.0.0.dist-info/top_level.txt
dify_file_parser-1.0.0.dist-info/RECORD
