Metadata-Version: 2.4
Name: dify-file-parser
Version: 1.0.0
Summary: 基于 Dify 项目文件处理功能抽离的通用文件解析器
Home-page: https://github.com/javen-yan/file-parser
Author: Javen Yan
Author-email: javen.yan@example.com
Classifier: Development Status :: 4 - Beta
Classifier: Intended Audience :: Developers
Classifier: License :: OSI Approved :: MIT License
Classifier: Operating System :: OS Independent
Classifier: Programming Language :: Python :: 3
Classifier: Programming Language :: Python :: 3.8
Classifier: Programming Language :: Python :: 3.9
Classifier: Programming Language :: Python :: 3.10
Classifier: Programming Language :: Python :: 3.11
Classifier: Topic :: Software Development :: Libraries :: Python Modules
Classifier: Topic :: Text Processing :: General
Requires-Python: >=3.8
License-File: LICENSE
Requires-Dist: aiofiles>=23.2.1
Requires-Dist: asyncio-throttle>=1.0.2
Requires-Dist: pandas>=2.1.3
Requires-Dist: PyPDF2>=3.0.1
Requires-Dist: pdfplumber>=0.10.3
Requires-Dist: pymupdf>=1.23.8
Requires-Dist: python-docx>=0.8.11
Requires-Dist: openpyxl>=3.1.2
Requires-Dist: python-pptx>=0.6.23
Requires-Dist: Pillow>=10.0.1
Requires-Dist: pytesseract>=0.3.10
Requires-Dist: opencv-python>=4.8.1.78
Requires-Dist: chardet>=5.2.0
Requires-Dist: markdown>=3.5.1
Requires-Dist: aiohttp>=3.8.6
Requires-Dist: loguru>=0.7.2
Requires-Dist: pydantic>=2.4.2
Requires-Dist: pytest>=7.4.3
Requires-Dist: pytest-asyncio>=0.21.1
Requires-Dist: pytest-cov>=4.1.0
Provides-Extra: dev
Requires-Dist: pytest>=7.4.3; extra == "dev"
Requires-Dist: pytest-asyncio>=0.21.1; extra == "dev"
Requires-Dist: pytest-cov>=4.1.0; extra == "dev"
Requires-Dist: black>=23.0.0; extra == "dev"
Requires-Dist: flake8>=6.0.0; extra == "dev"
Requires-Dist: mypy>=1.5.0; extra == "dev"
Provides-Extra: ocr
Requires-Dist: pytesseract>=0.3.10; extra == "ocr"
Requires-Dist: opencv-python>=4.8.1.78; extra == "ocr"
Dynamic: author
Dynamic: author-email
Dynamic: classifier
Dynamic: description
Dynamic: description-content-type
Dynamic: home-page
Dynamic: license-file
Dynamic: provides-extra
Dynamic: requires-dist
Dynamic: requires-python
Dynamic: summary
